{
  "project_info": {
    "project_number": "1011360830885",
    "project_id": "login-firebase-fe85b",
    "storage_bucket": "login-firebase-fe85b.appspot.com"
  },
  "client": [
    {
      "client_info": {
        "mobilesdk_app_id": "1:1011360830885:android:a74e0b73711c9d45bcc44c",
        "android_client_info": {
          "package_name": "com.example.loginfirebase"
        }
      },
      "oauth_client": [
        {
          "client_id": "1011360830885-8v68oku5df0k16vsndq9sdrlmu4d0o6g.apps.googleusercontent.com",
          "client_type": 3
        }
      ],
      "api_key": [
        {
          "current_key": "AIzaSyBLGxpZmGUOiI7xgDGzaFw9KaV4vdNtWkw"
        }
      ],
      "services": {
        "appinvite_service": {
          "other_platform_oauth_client": [
            {
              "client_id": "1011360830885-8v68oku5df0k16vsndq9sdrlmu4d0o6g.apps.googleusercontent.com",
              "client_type": 3
            }
          ]
        }
      }
    }
  ],
  "configuration_version": "1"
}